<?xml version="1.0" encoding="utf-8"?>
<Recent>
  <File>C:\GitHub\Programing\tkEngine2\GameTemplate\tkTools\Effekseer132\Sample\01_NextSoft01\MagicWater.efkproj</File>
  <File>C:\GitHub\Programing\tkEngine2\GameTemplate\tkTools\Effekseer132\Sample\01_NextSoft01\MagicMeteo.efkproj</File>
  <File>C:\GitHub\Programing\tkEngine2\GameTemplate\tkTools\Effekseer132\Sample\01_NextSoft01\Spear2.efkproj</File>
  <File>C:\GitHub\Programing\tkEngine2\GameTemplate\tkTools\Effekseer132\Sample\01_NextSoft01\MagicHeal1.efkproj</File>
  <File>C:\GitHub\Programing\tkEngine2\GameTemplate\tkTools\Effekseer132\Sample\01_NextSoft01\MagicCold.efkproj</File>
  <File>C:\GitHub\Programing\tkEngine2\GameTemplate\tkTools\Effekseer132\Sample\01_NextSoft01\MagicDark.efkproj</File>
  <File>C:\GitHub\Programing\tkEngine2\GameTemplate\tkTools\Effekseer132\Sample\01_NextSoft01\HealPotion1.efkproj</File>
  <File>C:\GitHub\Programing\tkEngine2\GameTemplate\tkTools\Effekseer132\Sample\01_NextSoft01\MagicThunder.efkproj</File>
  <File>C:\GitHub\Programing\tkEngine2\GameTemplate\tkTools\Effekseer132\Sample\01_NextSoft01\MagicShield.efkproj</File>
  <File>C:\GitHub\Programing\tkEngine2\GameTemplate\tkTools\Effekseer132\Sample\01_NextSoft01\Sword2.efkproj</File>
</Recent>